microscopemetrics_schema/_version.py
microscopemetrics_schema/datamodel/__init__.py
microscopemetrics_schema/datamodel/microscopemetrics_schema.py
microscopemetrics_schema/schema/analyses/argolight_schema.yaml
microscopemetrics_schema/schema/analyses/field_illumination.yaml
microscopemetrics_schema/schema/analyses/light_source_power.yaml
microscopemetrics_schema/schema/analyses/psf_beads.yaml
microscopemetrics_schema/schema/analyses/user_experiment.yaml
microscopemetrics_schema/schema/core.yaml
microscopemetrics_schema/schema/microscopemetrics_schema.yaml
microscopemetrics_schema/schema/samples/beads.yaml
microscopemetrics_schema/schema/samples/homogeneous_field.yaml
microscopemetrics_schema/schema/samples/light_source_power.yaml
microscopemetrics_schema/schema/samples/user_sample.yaml
microscopemetrics_schema/strategies/__init__.py
microscopemetrics_schema/strategies/analyses/__init__.py
microscopemetrics_schema/strategies/analyses/field_illumination_strategies.py
microscopemetrics_schema/strategies/analyses/light_source_power_strategies.py
microscopemetrics_schema/strategies/analyses/psf_beads_strategies.py
microscopemetrics_schema/strategies/analyses/user_experiment_strategies.py
microscopemetrics_schema/strategies/samples/__init__.py
microscopemetrics_schema/strategies/samples/homogeneous_field_strategies.py
microscopemetrics_schema/strategies/samples/psf_beads_strategies.py
microscopemetrics_schema/strategies/samples/user_experiment_strategies.py
microscopemetrics_schema-0.0.4.dist-info/LICENSE
microscopemetrics_schema-0.0.4.dist-info/METADATA
microscopemetrics_schema-0.0.4.dist-info/WHEEL
microscopemetrics_schema-0.0.4.dist-info/RECORD
