Metadata-Version: 2.3
Name: microscopemetrics_schema
Version: 0.0.4
Summary: A schema for microscope-metrics, a python package for microscope QC
License: GNU GPL v3.0
Author: Julio Mateos Langerak
Author-email: <julio.mateos-langerak@igh.cnrs.fr>
Requires-Python: >=3.9.18,<4.0
Classifier: License :: Other/Proprietary License
Classifier: Programming Language :: Python :: 3
Classifier: Programming Language :: Python :: 3.10
Classifier: Programming Language :: Python :: 3.11
Classifier: Programming Language :: Python :: 3.12
Classifier: Programming Language :: Python :: 3.13
Requires-Dist: hypothesis (>=6.131.15)
Requires-Dist: linkml-runtime (>=1.1.24)
